<?xml version="1.0" encoding="UTF-8"?>
<objects serializationModel="Studio.02.01.00">
	<object class="AudioFile" id="{42b335fe-bc74-4d80-873b-cc173c058995}">
		<property name="assetPath">
			<value>Explode - Gargantuan.ogg</value>
		</property>
		<property name="frequencyInKHz">
			<value>48</value>
		</property>
		<property name="channelCount">
			<value>2</value>
		</property>
		<property name="length">
			<value>4.5</value>
		</property>
		<relationship name="masterAssetFolder">
			<destination>{a568019a-8803-467d-8d03-ad6b2e128b63}</destination>
		</relationship>
	</object>
</objects>
